Metadata-Version: 1.1
Name: preprocessingtext
Version: 0.0.2
Summary: A series of methods to help you work pre processing of text in general, like stem, tokenizer and others.
Home-page: https://github.com/EvertonTomalok/preprocessingtext
Author: Everton Tomalok
Author-email: evertontomalok123@gmail.com
License: MIT
Download-URL: https://github.com/EvertonTomalok/preprocessingtext/archive/master.zip
Keywords: pre-processing text
Platform: UNKNOWN
Classifier: Programming Language :: Python :: 3
Classifier: License :: OSI Approved :: MIT License
Classifier: Operating System :: OS Independent
